[{"tor_name":"Game of Thrones S03E09 HDTV x264-EVOLVE [eztv]","url":"http:\/\/thepiratebay.sx\/torrent\/8534627\/Game_of_Thrones_S03E09_HDTV_x264-EVOLVE_[eztv]","url_mag":"magnet:?xt=urn:btih:e756b6ed7f1f647db2ea7e153e2fdc6226218a1f&dn=Game+of+Thrones+S03E09+HDTV+x264-EVOLVE+%5Beztv%5D&tr=udp%3A%2F%2Ftracker.openbittorrent.com%3A80&tr=udp%3A%2F%2Ftracker.publicbt.com%3A80&tr=udp%3A%2F%2Ftracker.istole.it%3A6969&tr=udp%3A%2F%2Ftracker.ccc.de%3A80&tr=udp%3A%2F%2Fopen.demonii.com%3A1337","desc":"Uploaded Today\u00a004:36, Size 329.84\u00a0MiB, ULed by eztv","size":["329.84","329.84"],"unit":["MiB","MiB"]},{"tor_name":"Game.of.Thrones.S03E09.720p.HDTV.x264-EVOLVE [PublicHD]","url":"http:\/\/thepiratebay.sx\/torrent\/8534520\/Game.of.Thrones.S03E09.720p.HDTV.x264-EVOLVE_[PublicHD]","url_mag":"magnet:?xt=urn:btih:89484c5c5b42f1fa55e178bb9dec85f13e483d93&dn=Game.of.Thrones.S03E09.720p.HDTV.x264-EVOLVE+%5BPublicHD%5D&tr=udp%3A%2F%2Ftracker.openbittorrent.com%3A80&tr=udp%3A%2F%2Ftracker.publicbt.com%3A80&tr=udp%3A%2F%2Ftracker.istole.it%3A6969&tr=udp%3A%2F%2Ftracker.ccc.de%3A80&tr=udp%3A%2F%2Fopen.demonii.com%3A1337","desc":"Uploaded Today\u00a004:01, Size 1.19\u00a0GiB, ULed by DibyaTPB","size":["1.19","1.19"],"unit":["GiB","","GiB"]},{"tor_name":"Jack.the.Giant.Slayer.2013.BRRip.XviD-S4A","url":"http:\/\/thepiratebay.sx\/torrent\/8523895\/Jack.the.Giant.Slayer.2013.BRRip.XviD-S4A","url_mag":"magnet:?xt=urn:btih:e9ad6d053226a2e60f10505a806f7b9083fd32aa&dn=Jack.the.Giant.Slayer.2013.BRRip.XviD-S4A&tr=udp%3A%2F%2Ftracker.openbittorrent.com%3A80&tr=udp%3A%2F%2Ftracker.publicbt.com%3A80&tr=udp%3A%2F%2Ftracker.istole.it%3A6969&tr=udp%3A%2F%2Ftracker.ccc.de%3A80&tr=udp%3A%2F%2Fopen.demonii.com%3A1337","desc":"Uploaded 05-31\u00a005:42, Size 705.79\u00a0MiB, ULed by scene4all","size":["705.79","705.79"],"unit":["MiB","MiB"]},{"tor_name":"Game of Thrones S03E09 HDTV x264-EVOLVE[ettv]","url":"http:\/\/thepiratebay.sx\/torrent\/8534590\/Game_of_Thrones_S03E09_HDTV_x264-EVOLVE[ettv]","url_mag":"magnet:?xt=urn:btih:920a3dc9dc71f28c8c526282157db79f7cded130&dn=Game+of+Thrones+S03E09+HDTV+x264-EVOLVE%5Bettv%5D&tr=udp%3A%2F%2Ftracker.openbittorrent.com%3A80&tr=udp%3A%2F%2Ftracker.publicbt.com%3A80&tr=udp%3A%2F%2Ftracker.istole.it%3A6969&tr=udp%3A%2F%2Ftracker.ccc.de%3A80&tr=udp%3A%2F%2Fopen.demonii.com%3A1337","desc":"Uploaded Today\u00a004:22, Size 329.84\u00a0MiB, ULed by ettv","size":["329.84","329.84"],"unit":["MiB","MiB"]},{"tor_name":"Game of Thrones S03E09 720p HDTV x264-EVOLVE [eztv]","url":"http:\/\/thepiratebay.sx\/torrent\/8534626\/Game_of_Thrones_S03E09_720p_HDTV_x264-EVOLVE_[eztv]","url_mag":"magnet:?xt=urn:btih:94b7b67095fd24a7f94371cab066c065fdb0a617&dn=Game+of+Thrones+S03E09+720p+HDTV+x264-EVOLVE+%5Beztv%5D&tr=udp%3A%2F%2Ftracker.openbittorrent.com%3A80&tr=udp%3A%2F%2Ftracker.publicbt.com%3A80&tr=udp%3A%2F%2Ftracker.istole.it%3A6969&tr=udp%3A%2F%2Ftracker.ccc.de%3A80&tr=udp%3A%2F%2Fopen.demonii.com%3A1337","desc":"Uploaded Today\u00a004:35, Size 1.19\u00a0GiB, ULed by eztv","size":["1.19","1.19"],"unit":["GiB","","GiB"]}]